uu_battery/__init__.py
uu_battery/core.py
uu_battery/helpers.py
uu_battery-0.2.1.dist-info/METADATA
uu_battery-0.2.1.dist-info/WHEEL
uu_battery-0.2.1.dist-info/licenses/LICENSE
uu_battery-0.2.1.dist-info/RECORD
