Metadata-Version: 2.4
Name: uu_battery
Version: 0.2.1
Summary: A package for interacting with the uu battery data handler project
Project-URL: UU-Battery-Data-Handler, https://github.com/fabianwilson/UU-Battery-Data-Handler
Author-email: Abbe Tanndal <abbe.tanndal@gmail.com>
License-Expression: MIT
License-File: LICENSE
Classifier: Operating System :: OS Independent
Classifier: Programming Language :: Python :: 3
Requires-Python: >=3.9
